ai_dynamo_runtime-0.7.1.dist-info/METADATA
ai_dynamo_runtime-0.7.1.dist-info/WHEEL
ai_dynamo_runtime-0.7.1.dist-info/licenses/LICENSE
dynamo/_core.abi3.so
dynamo/_core.pyi
dynamo/health_check.py
dynamo/llm/__init__.py
dynamo/llm/exceptions.py
dynamo/logits_processing/__init__.py
dynamo/logits_processing/base.py
dynamo/logits_processing/examples/__init__.py
dynamo/logits_processing/examples/hello_world.py
dynamo/logits_processing/examples/temperature.py
dynamo/nixl_connect/__init__.py
dynamo/prometheus_metrics.py
dynamo/prometheus_metrics.pyi
dynamo/prometheus_names.py
dynamo/runtime/__init__.py
dynamo/runtime/logging.py
ai_dynamo_runtime-0.7.1.dist-info/RECORD
