Metadata-Version: 2.4
Name: ai-dynamo-runtime
Version: 0.7.1
Classifier: Development Status :: 4 - Beta
Classifier: Intended Audience :: Developers
Classifier: Intended Audience :: Science/Research
Classifier: Intended Audience :: Information Technology
Classifier: License :: OSI Approved :: Apache Software License
Classifier: Programming Language :: Python :: 3
Classifier: Programming Language :: Python :: 3.10
Classifier: Programming Language :: Python :: 3.11
Classifier: Programming Language :: Python :: 3.12
Classifier: Topic :: Scientific/Engineering
Classifier: Topic :: Scientific/Engineering :: Artificial Intelligence
Classifier: Operating System :: POSIX :: Linux
Requires-Dist: pydantic>=2.10.6,<=2.11.7
Requires-Dist: uvloop>=0.21.0
License-File: LICENSE
Summary: Dynamo Inference Framework Runtime
Keywords: llm,genai,inference,nvidia,distributed,dynamo
Home-Page: https://github.com/ai-dynamo/dynamo
Author-email: "NVIDIA Inc." <sw-dl-dynamo@nvidia.com>
License: Apache-2.0
Requires-Python: >=3.10
